fibonacci/__init__.py
fibonacci/myfibo.py
fibonacci_pkg_RasVeet34-0.0.2.dist-info/LICENSE
fibonacci_pkg_RasVeet34-0.0.2.dist-info/METADATA
fibonacci_pkg_RasVeet34-0.0.2.dist-info/WHEEL
fibonacci_pkg_RasVeet34-0.0.2.dist-info/top_level.txt
fibonacci_pkg_RasVeet34-0.0.2.dist-info/RECORD
