Metadata-Version: 2.1
Name: fibonacci-pkg-RasVeet34
Version: 0.0.2
Summary: Printing fibonacci Numbers
Home-page: UNKNOWN
Author: Richard Sharp
Author-email: richardsharp.34@gmail.com
License: UNKNOWN
Platform: UNKNOWN
Classifier: Programming Language :: Python :: 3
Classifier: License :: OSI Approved :: MIT License
Classifier: Operating System :: OS Independent
Requires-Python: >=3.6
License-File: LICENSE
